[
  {
    "id": "f0ed51c8-ba15-4308-99bf-f9e156cf6642",
    "data": [
      {
        "text": "I cannot see anything",
        "userDefined": false
      }
    ],
    "isTemplate": false,
    "count": 0,
    "updated": 1540993380
  },
  {
    "id": "88736c7f-fe87-443e-b000-0776577bd56b",
    "data": [
      {
        "text": "I want more light in the hall",
        "userDefined": false
      }
    ],
    "isTemplate": false,
    "count": 0,
    "updated": 1540993380
  },
  {
    "id": "11647941-d5c9-476e-b900-18b8f0a661cf",
    "data": [
      {
        "text": "Switch on the light in the hall",
        "userDefined": false
      }
    ],
    "isTemplate": false,
    "count": 0,
    "updated": 1540993380
  },
  {
    "id": "25113014-3e96-4ed6-b061-83851b8c44e9",
    "data": [
      {
        "text": "Why is it so dark",
        "userDefined": false
      }
    ],
    "isTemplate": false,
    "count": 0,
    "updated": 1540993380
  }
]